gpioone/__init__.py
gpioone/adc.py
gpioone/adc_devices.py
gpioone/example_help.py
gpioone/lcd_display.py
gpioone/rgb_led.py
gpioone/shift_register.py
gpioone/steppers.py
gpioone-0.1.0.dist-info/LICENSE
gpioone-0.1.0.dist-info/METADATA
gpioone-0.1.0.dist-info/WHEEL
gpioone-0.1.0.dist-info/top_level.txt
gpioone-0.1.0.dist-info/RECORD
