Metadata-Version: 2.1
Name: gpioone
Version: 0.1.0
Summary: Interfaces for various GPIO devices on Raspberry PI
Home-page: https://github.com/grant-olson/gpioone
Author: Grant T. Olson
Author-email: kgo@grant-olson.net
License: UNKNOWN
Platform: UNKNOWN
Classifier: License :: OSI Approved :: BSD License
Classifier: Programming Language :: Python :: 2
Classifier: Programming Language :: Python :: 3
Classifier: Operating System :: OS Independent
